timeback_edubridge/__init__.py
timeback_edubridge/client.py
timeback_edubridge/constants.py
timeback_edubridge/exceptions.py
timeback_edubridge/py.typed
timeback_edubridge/utils.py
timeback_edubridge/lib/__init__.py
timeback_edubridge/lib/pagination.py
timeback_edubridge/lib/transport.py
timeback_edubridge/resources/__init__.py
timeback_edubridge/resources/analytics.py
timeback_edubridge/resources/applications.py
timeback_edubridge/resources/enrollments.py
timeback_edubridge/resources/learning_reports.py
timeback_edubridge/resources/subject_track.py
timeback_edubridge/resources/users.py
timeback_edubridge/types/__init__.py
timeback_edubridge/types/analytics.py
timeback_edubridge/types/applications.py
timeback_edubridge/types/base.py
timeback_edubridge/types/enrollments.py
timeback_edubridge/types/learning_reports.py
timeback_edubridge/types/subject_track.py
timeback_edubridge/types/users.py
timeback_edubridge-0.1.4.dist-info/METADATA
timeback_edubridge-0.1.4.dist-info/WHEEL
timeback_edubridge-0.1.4.dist-info/RECORD
